exasol/toolbox/__init__.py
exasol/toolbox/cli.py
exasol/toolbox/config.py
exasol/toolbox/error.py
exasol/toolbox/metrics.py
exasol/toolbox/nox/__init__.py
exasol/toolbox/nox/_artifacts.py
exasol/toolbox/nox/_ci.py
exasol/toolbox/nox/_dependencies.py
exasol/toolbox/nox/_documentation.py
exasol/toolbox/nox/_format.py
exasol/toolbox/nox/_lint.py
exasol/toolbox/nox/_metrics.py
exasol/toolbox/nox/_package.py
exasol/toolbox/nox/_package_version.py
exasol/toolbox/nox/_release.py
exasol/toolbox/nox/_shared.py
exasol/toolbox/nox/_test.py
exasol/toolbox/nox/plugin.py
exasol/toolbox/nox/tasks.py
exasol/toolbox/py.typed
exasol/toolbox/sphinx/__init__.py
exasol/toolbox/sphinx/github.py
exasol/toolbox/sphinx/multiversion/__init__.py
exasol/toolbox/sphinx/multiversion/__main__.py
exasol/toolbox/sphinx/multiversion/git.py
exasol/toolbox/sphinx/multiversion/main.py
exasol/toolbox/sphinx/multiversion/sphinx.py
exasol/toolbox/sphinx/multiversion/templates/multiversion-index.html
exasol/toolbox/templates/github/ISSUE_TEMPLATE/blank.md
exasol/toolbox/templates/github/ISSUE_TEMPLATE/bug.md
exasol/toolbox/templates/github/ISSUE_TEMPLATE/documentation.md
exasol/toolbox/templates/github/ISSUE_TEMPLATE/feature.md
exasol/toolbox/templates/github/ISSUE_TEMPLATE/refactoring.md
exasol/toolbox/templates/github/ISSUE_TEMPLATE/security.md
exasol/toolbox/templates/github/dependabot.yml
exasol/toolbox/templates/github/pull_request_template.md
exasol/toolbox/templates/github/workflows/build-and-publish.yml
exasol/toolbox/templates/github/workflows/cd.yml
exasol/toolbox/templates/github/workflows/check-release-tag.yml
exasol/toolbox/templates/github/workflows/checks.yml
exasol/toolbox/templates/github/workflows/ci.yml
exasol/toolbox/templates/github/workflows/gh-pages.yml
exasol/toolbox/templates/github/workflows/matrix-all.yml
exasol/toolbox/templates/github/workflows/matrix-exasol.yml
exasol/toolbox/templates/github/workflows/matrix-python.yml
exasol/toolbox/templates/github/workflows/merge-gate.yml
exasol_toolbox-5.1.0.dist-info/METADATA
exasol_toolbox-5.1.0.dist-info/WHEEL
exasol_toolbox-5.1.0.dist-info/entry_points.txt
exasol_toolbox-5.1.0.dist-info/licenses/LICENSE
exasol_toolbox-5.1.0.dist-info/RECORD
